pypicpay/__init__.py
pypicpay/picpay.py
pypicpay-0.4.8.dist-info/LICENSE
pypicpay-0.4.8.dist-info/METADATA
pypicpay-0.4.8.dist-info/WHEEL
pypicpay-0.4.8.dist-info/RECORD
