Metadata-Version: 2.1
Name: pypicpay
Version: 0.4.8
Summary: Aceite PicPay e faça parte do movimento que está revolucionando a relação com o dinheiro no Brasil.
Home-page: https://github.com/hudsonbrendon/picpay#readme
License: MIT
Author: Hudson Brendon
Author-email: contato.hudsonbrendon@gmail.com
Requires-Python: >=3.8,<4.0
Classifier: License :: OSI Approved :: MIT License
Classifier: Programming Language :: Python :: 3
Classifier: Programming Language :: Python :: 3.8
Classifier: Programming Language :: Python :: 3.9
Classifier: Programming Language :: Python :: 3.10
Classifier: Programming Language :: Python :: 3.11
Classifier: Programming Language :: Python :: 3.12
Requires-Dist: requests
Project-URL: Repository, https://github.com/hudsonbrendon/picpay
